Metadata-Version: 2.1
Name: creditagricole-particuliers
Version: 0.13.0
Summary: Python client pour la banque Crédit Agricole
Home-page: https://github.com/dmachard/creditagricole-particuliers
Author: Denis MACHARD
Author-email: d.machard@gmail.com
Keywords: credit agricole api banking banque
Platform: any
Classifier: License :: OSI Approved :: MIT License
Classifier: Programming Language :: Python :: 3
Classifier: Operating System :: OS Independent
Classifier: Topic :: Software Development :: Libraries
License-File: LICENSE
